jwt_parser/__init__.py
jwt_parser/token_parser.py
jwt_parser-0.1.1.dist-info/METADATA
jwt_parser-0.1.1.dist-info/WHEEL
jwt_parser-0.1.1.dist-info/top_level.txt
jwt_parser-0.1.1.dist-info/RECORD
